[{"id":"461959","price":"22.0","s":"305","r":6710,"title":"Full Head of Colour With MOROCCANOIL™ Treatment, Haircut and Finish for £22 at The Style Lounge (Up to £93 Value)","url":"http://www.groupon.co.uk/deals/birmingham/style-lounge/461959","discount_percent":"76.0","highlights":"<ul>\r\n<li>Choice of foils or full head of semi-permanent colour</li>\r\n<li>Four stars in The Good Salon Guide</li>\r\n<li>\r\n10% off hair products on day and 10% off next visit</li>\r\n<li>\r\nAuthorised distributors of MOROCCANOIL™, Tigi, and Racoon products</li>\r\n<li>Newly refurbished salon </li>\r\n<li>Sunday appointments available</li>\r\n</ul>","image_large_url":"http://static.groupon.co.uk/28/56/1308309945628.jpg","type_info":"MAIN_DEAL","salesforce_id":"00193160"},{"id":"465001","price":"59.0","s":"20","r":1180,"title":"£59 for a £180 Voucher Towards Facial Cosmetic Treatment of Choice at CHC Cosmetics","url":"http://www.groupon.co.uk/deals/birmingham/CHCMedical/465001","discount_percent":"67.0","highlights":"<ul>\r\n<li>Includes\r\na consultation</li>\r\n<li>Treat\r\nany one facial area to help reduce the appearance of fine lines and wrinkles</li>\r\n<li>Further\r\nareas available for £60 per area if booked during first consultation </li>\r\n<li>Free\r\nparking</li>\r\n</ul>","image_large_url":"http://static.groupon.co.uk/78/08/1302889390878.jpg","type_info":"SIDE_DEAL","salesforce_id":"00244157"}]